rfc3161ng/__init__.py
rfc3161ng/api.py
rfc3161ng/constants.py
rfc3161ng/types.py
rfc3161ng-2.1.3.dist-info/LICENSE
rfc3161ng-2.1.3.dist-info/METADATA
rfc3161ng-2.1.3.dist-info/WHEEL
rfc3161ng-2.1.3.dist-info/top_level.txt
rfc3161ng-2.1.3.dist-info/RECORD
