Metadata-Version: 2.1
Name: rfc3161ng
Version: 2.1.3
Summary: Python implementation of the RFC3161 specification, using pyasn1
Home-page: https://dev.entrouvert.org/projects/python-rfc3161
Author: Benjamin Dauvergne
Author-email: bdauvergne@entrouvert.com
Maintainer: trbs
Maintainer-email: trbs@trbs.net
License: MIT
Platform: any
Classifier: Environment :: Console
Classifier: Intended Audience :: Developers
Classifier: Intended Audience :: Information Technology
Classifier: Intended Audience :: System Administrators
Classifier: License :: OSI Approved :: MIT License
Classifier: Operating System :: OS Independent
Classifier: Programming Language :: Python :: 2.7
Classifier: Programming Language :: Python :: 3.6
Classifier: Topic :: Communications
Classifier: Topic :: Software Development :: Libraries :: Python Modules
